walletlib/__init__.py
walletlib/base32.py
walletlib/bitcoinj_compat.py
walletlib/coinomi_proto.py
walletlib/crypto.py
walletlib/exceptions.py
walletlib/protobufwallet.py
walletlib/scripts/__init__.py
walletlib/scripts/dumpwallet.py
walletlib/utils.py
walletlib/wallet_segwit.py
walletlib/walletdat.py
walletlib-0.2.10.dist-info/entry_points.txt
walletlib-0.2.10.dist-info/LICENSE.md
walletlib-0.2.10.dist-info/WHEEL
walletlib-0.2.10.dist-info/METADATA
walletlib-0.2.10.dist-info/RECORD
